uws/__init__.py
uws/linux/uwebsocketspy.so
uws/macosx/uwebsocketspy.so
uws-0.0.9.dist-info/METADATA
uws-0.0.9.dist-info/WHEEL
uws-0.0.9.dist-info/RECORD
